Metadata-Version: 2.1
Name: cropyble
Version: 1.2.0
Summary: Cropyble is a module that allows a user to easily perform crops on an image containing recognizable text. This module utilizes optical character recognition (OCR) from Google by way of pytesseract.
Home-page: https://github.com/SkylerBurger/cropyble
Author: Skyler Burger
Author-email: skylerburger@gmail.com
License: MIT
Download-URL: https://github.com/SkylerBurger/cropyble/archive/1.2.1.tar.gz
Keywords: OCR,tesseract,pytesseract,crop,character recognition
Platform: UNKNOWN
Classifier: Development Status :: 4 - Beta
Classifier: Intended Audience :: Developers
Classifier: Topic :: Software Development :: Build Tools
Classifier: License :: OSI Approved :: MIT License
Classifier: Programming Language :: Python :: 3.7
